Metadata-Version: 1.0
Name: mapkit
Version: 1.2.3
Summary: Mapping tools for PostGIS-enabled PostgreSQL databases.
Home-page: https://github.com/CI-WATER/mapkit
Author: Nathan Swain
Author-email: nathan.swain@byu.net
License: BSD 2-Clause License
Keywords: PostGIS,map,GIS
Platform: UNKNOWN
